{
  "$schema_note": "Binds each task type to its substrate pieces. The boot sequence reads this to know which files to load.",
  "version": "1.0",
  "workflows": {
    "net_sec_hardening": {
      "project": "dominion",
      "spec": "workflows/workflow_net_sec_hardening.md",
      "skeleton": "Security audit",
      "decomposition": "home_network_security_hardening",
      "tradeoff_pattern": "security_control_table",
      "evidence_rules": "patterns/evidence_rules.md",
      "failure_modes": ["non-home-executable", "monitoring-handwave", "prevention-only", "constraint-overfit"]
    },
    "ui_surface_design": {
      "project": "dominion",
      "spec": "workflows/workflow_ui_surface_design.md",
      "skeleton": "Design",
      "decomposition": "ui_surface",
      "tradeoff_pattern": "architecture_tradeoff_table",
      "evidence_rules": "patterns/evidence_rules.md",
      "failure_modes": ["single-option", "evidence-gap", "schema-drift", "state-gap"]
    }
  }
}
